django_multipleimageinput/__init__.py
django_multipleimageinput/file.py
django_multipleimageinput/forms.py
django_multipleimageinput/views.py
django_multipleimageinput/widgets.py
django_multipleimageinput/static/django_multipleimageinput/multipleimageinput.css
django_multipleimageinput/static/django_multipleimageinput/multipleimageinput.js
django_multipleimageinput/templates/django_multipleimageinput/multipleimageinput.html
django_multipleimageinput-0.0.2.dist-info/LICENSE
django_multipleimageinput-0.0.2.dist-info/METADATA
django_multipleimageinput-0.0.2.dist-info/WHEEL
django_multipleimageinput-0.0.2.dist-info/top_level.txt
django_multipleimageinput-0.0.2.dist-info/RECORD
