Metadata-Version: 2.1
Name: django-multipleimageinput
Version: 0.0.2
Summary: Django widget for multiple image input
Home-page: https://github.com/eugen1j/django-multipleimageinput
Author: eugen1j
Author-email: eugenij.bondar@gmail.com
License: MIT
Keywords: python3
Platform: UNKNOWN
Classifier: License :: OSI Approved :: MIT License
Classifier: Programming Language :: Python
Classifier: Programming Language :: Python :: 3.7
Classifier: Development Status :: 5 - Production/Stable
Classifier: Operating System :: Unix
Classifier: Operating System :: Microsoft :: Windows
Classifier: Operating System :: MacOS
Requires-Python: >=3.7.0
Requires-Dist: django
